waylonwalker/__about__.py
waylonwalker/__init__.py
waylonwalker/__main__.py
waylonwalker/app.py
waylonwalker-0.4.6.dist-info/METADATA
waylonwalker-0.4.6.dist-info/WHEEL
waylonwalker-0.4.6.dist-info/entry_points.txt
waylonwalker-0.4.6.dist-info/licenses/LICENSE
waylonwalker-0.4.6.dist-info/RECORD
