Metadata-Version: 2.1
Name: waylonwalker
Version: 0.4.6
Summary: Waylon Walker's business card
Project-URL: Homepage, https://github.com/waylonwalker/waylonwalker-cli
Author: Waylon Walker
License: Copyright (c) 2012-2022 Waylon Walker
License-File: LICENSE
Keywords: None
Classifier: Development Status :: 4 - Beta
Classifier: Environment :: Plugins
Classifier: Intended Audience :: Developers
Classifier: Operating System :: MacOS
Classifier: Operating System :: Microsoft :: Windows
Classifier: Operating System :: POSIX :: Linux
Classifier: Programming Language :: Python :: 3.8
Classifier: Programming Language :: Python :: 3.9
Classifier: Programming Language :: Python :: 3.10
Classifier: Programming Language :: Python :: 3.11
Classifier: Typing :: Typed
Requires-Dist: httpx
Requires-Dist: textual
Requires-Dist: waylonwalker
Provides-Extra: dev
Requires-Dist: black; extra == 'dev'
Requires-Dist: ruff; extra == 'dev'
